Metadata-Version: 2.1
Name: dynamic-rename
Version: 0.0.5
Summary: Column rename  in pyspark dataframe
Home-page: UNKNOWN
Author-email: ranjitmaity95@gmail.com
License: UNKNOWN
Platform: UNKNOWN
